{
  "runtimeName": "std::array::size",
  "runtimeParameterDefinitions": [
    {
      "dataTypeIdentifier": {
        "genericType": {
          "dataTypeIdentifier": "ARRAY",
          "genericMappers": [
            {
              "source": [
                {
                  "genericKey": "R"
                }
              ],
              "target": "T",
              "genericCombinations": []
            }
          ]
        }
      },
      "runtimeName": "array",
      "defaultValue": null,
      "name": [
        {
          "code": "en-US",
          "content": "Array"
        }
      ],
      "description": [
        {
          "code": "en-US",
          "content": "The array whose number of elements is to be returned."
        }
      ],
      "documentation": [
        {
          "code": "en-US",
          "content": "Specifies the array for which the total number of elements will be calculated and returned."
        }
      ]
    }
  ],
  "returnTypeIdentifier": {
    "dataTypeIdentifier": "NUMBER"
  },
  "throwsError": false,
  "genericKeys": [
    "R"
  ],
  "name": [
    {
      "code": "en-US",
      "content": "Array Size"
    }
  ],
  "description": [
    {
      "code": "en-US",
      "content": "Returns the number of elements in the array."
    }
  ],
  "documentation": [
    {
      "code": "en-US",
      "content": "This function returns the count of elements present in the given array."
    }
  ],
  "deprecationMessage": []
}