{
  "runtime_name": "std::boolean::from_number",
  "runtime_parameter_definitions": [
    {
      "data_type_identifier": {
        "type": {
          "DataTypeIdentifier": "NUMBER"
        }
      },
      "runtime_name": "value",
      "default_value": null,
      "name": [
        {
          "code": "en-US",
          "content": "Value"
        }
      ],
      "description": [
        {
          "code": "en-US",
          "content": "The number to convert."
        }
      ],
      "documentation": [
        {
          "code": "en-US",
          "content": "Converts a number to a boolean value."
        }
      ]
    }
  ],
  "return_type_identifier": {
    "type": {
      "DataTypeIdentifier": "BOOLEAN"
    }
  },
  "throws_error": false,
  "generic_keys": [],
  "name": [
    {
      "code": "en-US",
      "content": "From Number"
    }
  ],
  "description": [
    {
      "code": "en-US",
      "content": "Will convert the number to a boolean."
    }
  ],
  "documentation": [
    {
      "code": "en-US",
      "content": "Converts a number to a boolean value. Typically, 0 maps to false and non-zero maps to true."
    }
  ],
  "deprecation_message": []
}