{
  "variant": "NODE",
  "identifier": "TRANSFORM",
  "name": [
    {
      "code": "en-US",
      "content": "Transform"
    }
  ],
  "rules": [
    {
      "returnType": {
        "dataTypeIdentifier": {
          "genericKey": "R"
        }
      }
    },
    {
      "inputTypes": {
        "inputTypes": [
          {
            "dataTypeIdentifier": {
              "genericKey": "I"
            },
            "inputIdentifier": "transform"
          }
        ]
      }
    }
  ],
  "genericKeys": [
    "I",
    "R"
  ]
}